aksconverter_properties_pkg/__init__.py
aksconverter_properties_pkg/aksconverter_properties.py
Aksconverter-0.0.5.dist-info/LICENCE.txt
Aksconverter-0.0.5.dist-info/METADATA
Aksconverter-0.0.5.dist-info/WHEEL
Aksconverter-0.0.5.dist-info/top_level.txt
Aksconverter-0.0.5.dist-info/RECORD
